pyworker/__init__.py
pyworker/db.py
pyworker/job.py
pyworker/logger.py
pyworker/reporter.py
pyworker/util.py
pyworker/worker.py
rubydj_pyworker-1.2.1.dist-info/LICENSE.txt
rubydj_pyworker-1.2.1.dist-info/METADATA
rubydj_pyworker-1.2.1.dist-info/WHEEL
rubydj_pyworker-1.2.1.dist-info/top_level.txt
rubydj_pyworker-1.2.1.dist-info/RECORD
