Metadata-Version: 2.1
Name: rubydj-pyworker
Version: 1.2.1
Summary: A pure Python worker for Ruby-based DelayedJobs with Newrelic reporting.
Home-page: https://github.com/rayyansys/pyworker
Author: Rayyan Systems, Inc.
Author-email: support@rayyan.ai
License: MIT
Platform: UNKNOWN
Classifier: Environment :: Web Environment
Classifier: Intended Audience :: Developers
Classifier: License :: OSI Approved :: MIT License
Classifier: Operating System :: OS Independent
Classifier: Programming Language :: Python
Classifier: Programming Language :: Python :: 3
Classifier: Programming Language :: Python :: 3 :: Only
Classifier: Programming Language :: Python :: 3.7
Classifier: Programming Language :: Python :: 3.8
Classifier: Programming Language :: Python :: 3.9
Classifier: Programming Language :: Python :: 3.10
Classifier: Programming Language :: Python :: 3.11
Classifier: Programming Language :: Python :: 3.12
Classifier: Topic :: Internet :: WWW/HTTP
Classifier: Topic :: Internet :: WWW/HTTP :: Dynamic Content
Requires-Python: >=3.7
Requires-Dist: psycopg2-binary>=2
Requires-Dist: python-dateutil>=2
Requires-Dist: PyYAML>=3
Requires-Dist: newrelic>=8.3.0
